AUTHORS.rst
CONTRIBUTING.rst
HISTORY.rst
LICENSE
MANIFEST.in
README.rst
setup.cfg
setup.py
bin/run_gms.py
bin/run_gms.sh
docs/Makefile
docs/about.rst
docs/algorithm_descriptions.rst
docs/authors.rst
docs/conf.py
docs/contributing.rst
docs/history.rst
docs/index.rst
docs/infrastructure.rst
docs/installation.rst
docs/make.bat
docs/usage.rst
docs/_build/html/_static/file.png
docs/_build/html/_static/minus.png
docs/_build/html/_static/plus.png
docs/images/webapp_screenshot_900x497.png
docs/infrastructure/ecmwf_db.rst
docs/infrastructure/postgresql_db.rst
docs/usage/add_new_data_manually.rst
docs/usage/add_new_data_to_the_database.rst
docs/usage/cli_run_gms.rst
docs/usage/create_new_jobs.rst
docs/usage/execute_jobs.rst
docs/usage/setting_a_configuration.rst
docs/usage/using_the_data_downloader.rst
gms_preprocessing/__init__.py
gms_preprocessing/version.py
gms_preprocessing.egg-info/PKG-INFO
gms_preprocessing.egg-info/SOURCES.txt
gms_preprocessing.egg-info/dependency_links.txt
gms_preprocessing.egg-info/not-zip-safe
gms_preprocessing.egg-info/requires.txt
gms_preprocessing.egg-info/top_level.txt
gms_preprocessing/algorithms/L1A_P.py
gms_preprocessing/algorithms/L1B_P.py
gms_preprocessing/algorithms/L1C_P.py
gms_preprocessing/algorithms/L2A_P.py
gms_preprocessing/algorithms/L2B_P.py
gms_preprocessing/algorithms/L2C_P.py
gms_preprocessing/algorithms/__init__.py
gms_preprocessing/algorithms/cloud_masking.py
gms_preprocessing/algorithms/geoprocessing.py
gms_preprocessing/database/cloud_classifier/S2__cld_mask_20160321_s2_8l0.200_11l0.060_12l0.040_v20161124_16:41:04.h5
gms_preprocessing/database/earth_sun_distance/Earth_Sun_distances_per_day_edited.csv
gms_preprocessing/database/snr/Sentinel-2A/MSI/SNR_model.csv
gms_preprocessing/database/solar_irradiance/SUNp1fontenla__350-2500nm_@0.1nm_converted.txt
gms_preprocessing/database/solar_irradiance/SUNp1fontenla__350-2500nm_converted.txt
gms_preprocessing/io/__init__.py
gms_preprocessing/io/input_reader.py
gms_preprocessing/io/output_writer.py
gms_preprocessing/misc/__init__.py
gms_preprocessing/misc/database_tools.py
gms_preprocessing/misc/definition_dicts.py
gms_preprocessing/misc/environment.py
gms_preprocessing/misc/exception_handler.py
