Metadata-Version: 2.1
Name: gms-preprocessing
Version: 0.19.2
Summary: GeoMultiSens - Scalable Multi-Sensor Analysis of Remote Sensing Data
Home-page: https://gitext.gfz-potsdam.de/geomultisens/gms_preprocessing
Author: Daniel Scheffler
Author-email: daniel.scheffler@gfz-potsdam.de
License: GPL-3.0-or-later
Keywords: gms_preprocessing
Platform: UNKNOWN
Classifier: Development Status :: 5 - Production/Stable
Classifier: Intended Audience :: Developers
Classifier: License :: OSI Approved :: GNU General Public License v3 or later (GPLv3+)
Classifier: Natural Language :: English
Classifier: Programming Language :: Python :: 3
Classifier: Programming Language :: Python :: 3.6
Classifier: Programming Language :: Python :: 3.7
Classifier: Programming Language :: Python :: 3.8
Classifier: Programming Language :: Python :: 3.9
Provides-Extra: doc
Provides-Extra: test
Provides-Extra: lint
Provides-Extra: dev
